{
    "0": "Armor of Karna",
    "1": "Armor of Achilles",
    "2": "Armor of Beowulf",
    "3": "Helmet of Rostam",
    "4": "Helm of Darkness",
    "5": "Crown of Immortality",
    "6": "Aegis",
    "7": "Shield of Achilles",
    "8": "Shield of Ajax",
    "9": "Shield of Joseph of Arimathea",
    "10": "Shield of Judas Maccabee",
    "11": "Shield of El Cid",
    "12": "Shield of Evalach",
    "13": "Shield of Vishnu",
    "14": "Cronus' scythe",
    "15": "Death's scythe",
    "16": "Astra",
    "17": "Gan Jiang and Mo Ye",
    "18": "Kusanagi-no-tsurugi",
    "19": "Sword of Attila",
    "20": "Sword of Peleus",
    "21": "Taming Sari",
    "22": "Shamshir-e Zomorrodnegar",
    "23": "Totsuka-no-Tsurugi",
    "24": "Caladbolg",
    "25": "Caledfwlch",
    "26": "Mac an Luin",
    "27": "Moralltach and Beagalltach",
    "28": "Nagelring",
    "29": "Blutgang",
    "30": "Hrunting",
    "31": "N\u00e6gling",
    "32": "Arondight",
    "33": "Carnwennan",
    "34": "Clarent",
    "35": "Coreiseuse",
    "36": "Excalibur",
    "37": "Grail Sword",
    "38": "Freyr's Sword",
    "39": "Hrotti",
    "40": "Legbiter",
    "41": "Mistilteinn",
    "42": "Quern-biter",
    "43": "Ridill",
    "44": "Skofnung",
    "45": "Tyrfing",
    "46": "Balisarda",
    "47": "Durendal",
    "48": "Froberge",
    "49": "Sauvagine",
    "50": "Ascalon",
    "51": "G\u00e1e Buide",
    "52": "G\u00e1e Bulg",
    "53": "Gungnir",
    "54": "Lance of Olyndicus",
    "55": "Lug's Spear",
    "56": "Nihongo",
    "57": "Otegine",
    "58": "Rhongomiant",
    "59": "Spear of Achilles",
    "60": "Poseidon's trident",
    "61": "Trishula",
    "62": "Holy Lance",
    "63": "Spear of Assal",
    "64": "Crann Buidhe",
    "65": "Apollo's bow",
    "66": "Artemis' bow",
    "67": "Brahmastra",
    "68": "Cupid's bow",
    "69": "Failnaught",
    "70": "Gandiva",
    "71": "Heracles's bow",
    "72": "Eurytus' bow",
    "73": "Caduceus",
    "74": "Rod of Asclepius",
    "75": "Thyrsus",
    "76": "Axe of Perun",
    "77": "Mj\u00f6lnir",
    "78": "Ukonvasara",
    "79": "Uchide no kozuchi",
    "80": "Parashu",
    "81": "Sharur",
    "82": "Yagrush and Ayamur",
    "83": "Kaladanda",
    "84": "Club of Dagda",
    "85": "Thunderbolt of Zeus",
    "86": "Vajra",
    "87": "Holly Dart",
    "88": "Arrow of Brahma",
    "89": "Tathlum",
    "90": "Sagitta",
    "91": "Aphrodite's Magic Girdle",
    "92": "Babr-e Bayan",
    "93": "Falcon Cloak",
    "94": "Girdle of Hippolyta",
    "95": "Hide of Leviathan",
    "96": "Hide of the Nemean lion",
    "97": "Mantle of Arthur",
    "98": "Pais Badarn Beisrydd",
    "99": "Shoes of V\u00ed\u00f0arr",
    "100": "Shirt of Nessus",
    "101": "Fast-walker Boots",
    "102": "Swan Cloak",
    "103": "Necklace of Harmonia",
    "104": "Necklace of the Lady of the Lake",
    "105": "Draupnir",
    "106": "Ring of Dispel",
    "107": "Ring of Mudarra",
    "108": "Ring of Gyges",
    "109": "Seal of Solomon",
    "110": "Dandu Monara",
    "111": "Flying carpet",
    "112": "Flying mortar and pestle of Baba Yaga",
    "113": "Warship Argo",
    "114": "Canoe of Gluskab",
    "115": "Canoe of M\u0101ui",
    "116": "Naglfar",
    "117": "Preserver of Life",
    "118": "Morning Boat Mandjet",
    "119": "Evening Boat Mesektet",
    "120": "Wave Sweeper",
    "121": "Flying Dutchman",
    "122": "Poseidon's chariot",
    "123": "Helios' chariot",
    "124": "Thor's chariot",
    "125": "Freyja's chariot",
    "126": "Selene's chariot",
    "127": "Sol's chariot",
    "128": "Four Treasures of the Tuatha D\u00e9 Danann",
    "129": "Three Sacred Treasures of Japan",
    "130": "Pandora's box",
    "131": "Yata no Kagami",
    "132": "Holy Grail",
    "133": "Agimat",
    "134": "Book of Thoth",
    "135": "Tablet of Destiny",
    "136": "Philosopher's stone",
    "137": "Stone of Giramphiel",
    "138": "Singasteinn",
    "139": "Adder stone",
    "140": "Toadstone",
    "141": "Stone of Scone",
    "142": "Lia F\u00e1il",
    "143": "Thunderstone",
    "144": "Gj\u00f6ll",
    "145": "Batrachite"
}